godule/__init__.py
godule/data_readers/__init__.py
godule/data_saving/__init__.py
godule/latex/__init__.py
godule/stats/__init__.py
godule/visualization/__init__.py
godule-0.1.0.dev0.dist-info/METADATA
godule-0.1.0.dev0.dist-info/WHEEL
godule-0.1.0.dev0.dist-info/top_level.txt
godule-0.1.0.dev0.dist-info/RECORD
